samino/__init__.py
samino/acm.py
samino/client.py
samino/local.py
samino-10.0.0.dist-info/LICENSE
samino-10.0.0.dist-info/METADATA
samino-10.0.0.dist-info/WHEEL
samino-10.0.0.dist-info/top_level.txt
samino-10.0.0.dist-info/RECORD
