Metadata-Version: 2.1
Name: samino
Version: 10.0.0
Summary: Amino Bots with python!
Home-page: https://github.com/SirLez/SAmino
Download-URL: https://github.com/SirLez/SAmino/archive/refs/heads/main.zip
Author: SirLez
Author-email: botsirlez@gmail.com
License: MIT
Keywords: api,python,python3,python3.x,SirLez,Bovonos,Amino,samino,samino pyS-Amino,samino,samino,samino-bot,samino-bots,samino-bot,ndc,narvii.apps,aminoapps,samino-py,samino,samino-bot,narvii
License-File: LICENSE
Requires-Dist: JSON-minify
Requires-Dist: setuptools
Requires-Dist: httpx
Requires-Dist: websocket-client (==1.3.1)
Requires-Dist: websockets
Requires-Dist: ujson
